taco/__init__.py
taco_train-0.0.0.dist-info/METADATA
taco_train-0.0.0.dist-info/WHEEL
taco_train-0.0.0.dist-info/top_level.txt
taco_train-0.0.0.dist-info/RECORD
